leximpact_socio_fisca_simu_etat/__init__.py
leximpact_socio_fisca_simu_etat/_nbdev.py
leximpact_socio_fisca_simu_etat/aggregates_build.py
leximpact_socio_fisca_simu_etat/aggregates_read.py
leximpact_socio_fisca_simu_etat/cache.py
leximpact_socio_fisca_simu_etat/config.py
leximpact_socio_fisca_simu_etat/csg_simu.py
leximpact_socio_fisca_simu_etat/logger.py
leximpact_socio_fisca_simu_etat/schema.py
leximpact_socio_fisca_simu_etat/status.py
leximpact_socio_fisca_simu_etat-0.1.9.dist-info/entry_points.txt
leximpact_socio_fisca_simu_etat-0.1.9.dist-info/LICENSE
leximpact_socio_fisca_simu_etat-0.1.9.dist-info/WHEEL
leximpact_socio_fisca_simu_etat-0.1.9.dist-info/METADATA
leximpact_socio_fisca_simu_etat-0.1.9.dist-info/RECORD
