Metadata-Version: 2.1
Name: leximpact-socio-fisca-simu-etat
Version: 0.1.9
Summary: French State Budget Simulation
Home-page: https://socio-fiscal.leximpact.an.fr/
License: AGPL-3.0-or-later
Author: Leximpact
Author-email: Leximpact@an.fr
Requires-Python: >=3.8,<4.0
Classifier: License :: OSI Approved :: GNU Affero General Public License v3 or later (AGPLv3+)
Classifier: Programming Language :: Python :: 3
Classifier: Programming Language :: Python :: 3.10
Classifier: Programming Language :: Python :: 3.8
Classifier: Programming Language :: Python :: 3.9
Provides-Extra: api
Requires-Dist: fastapi[api] (>=0.75.0,<0.76.0); extra == "api"
Requires-Dist: gunicorn[api] (>=20.1.0,<21.0.0); extra == "api"
Requires-Dist: openfisca-france-reforms (>=1.0.82)
Requires-Dist: pandas (>=1.2.4,<2.0.0)
Requires-Dist: prometheus-fastapi-instrumentator[api] (>=5.7.1,<6.0.0); extra == "api"
Requires-Dist: pydantic (>=1.9.0,<2.0.0)
Requires-Dist: python-decouple (>=3.5,<4.0)
Requires-Dist: python-jose[cryptography] (>=3.3.0,<4.0.0); extra == "api"
Requires-Dist: redis (>=3.5.3,<4.0.0)
Requires-Dist: ruamel.yaml (>=0.17.21,<0.18.0)
Requires-Dist: tables (>=3.6.1)
Requires-Dist: toolz (>=0.11.1)
Requires-Dist: uvicorn[standard] (>=0.13.4,<0.14.0); extra == "api"
Project-URL: Repository, https://git.leximpact.dev/leximpact/leximpact-socio-fiscal-simu-etat/
